MANIFEST.in
README.txt
setup.cfg
setup.py
docs/HISTORY.txt
docs/INSTALL.txt
docs/LICENSE.GPL
docs/LICENSE.txt
redomino/__init__.py
redomino/__init__.pyc
redomino.seosupport.egg-info/PKG-INFO
redomino.seosupport.egg-info/SOURCES.txt
redomino.seosupport.egg-info/dependency_links.txt
redomino.seosupport.egg-info/entry_points.txt
redomino.seosupport.egg-info/namespace_packages.txt
redomino.seosupport.egg-info/not-zip-safe
redomino.seosupport.egg-info/requires.txt
redomino.seosupport.egg-info/top_level.txt
redomino/seosupport/README.txt
redomino/seosupport/__init__.py
redomino/seosupport/__init__.pyc
redomino/seosupport/configure.zcml
redomino/seosupport/skins.zcml
redomino/seosupport/browser/__init__.py
redomino/seosupport/browser/__init__.pyc
redomino/seosupport/browser/configure.zcml
redomino/seosupport/browser/interfaces.py
redomino/seosupport/browser/interfaces.pyc
redomino/seosupport/browser/viewlets.py
redomino/seosupport/browser/viewlets.pyc
redomino/seosupport/profiles/default/browserlayer.xml
redomino/seosupport/profiles/default/jsregistry.xml
redomino/seosupport/profiles/default/metadata.xml
redomino/seosupport/profiles/default/propertiestool.xml
redomino/seosupport/profiles/default/skins.xml
redomino/seosupport/skins/redomino_seosupport/redomino_seo.js
redomino/seosupport/skins/redomino_seosupport/robots.txt
redomino/seosupport/tests/__init__.py
redomino/seosupport/tests/base.py
redomino/seosupport/tests/test_doctest.py
redomino/seosupport/tests/test_portal.py