Metadata-Version: 1.0
Name: redomino.seosupport
Version: 1.1
Summary: Installing this plugin you will get a Plone site with the sitemap.xml.gz enabled by default
Home-page: https://github.com/redomino/redomino.seosupport
Author: Davide Moro
Author-email: davide.moro@redomino.com
License: GPL
Keywords: plone seo
Platform: UNKNOWN
Classifier: Framework :: Plone
Classifier: Programming Language :: Python
